pytest_atomic.py
pytest_atomic-1.1.dist-info/METADATA
pytest_atomic-1.1.dist-info/RECORD
pytest_atomic-1.1.dist-info/WHEEL
pytest_atomic-1.1.dist-info/entry_points.txt
pytest_atomic-1.1.dist-info/top_level.txt
